AUTHORS.rst
CONTRIBUTING.rst
HISTORY.rst
LICENSE
MANIFEST.in
README.rst
setup.cfg
setup.py
docs/Makefile
docs/authors.rst
docs/conf.py
docs/contributing.rst
docs/history.rst
docs/index.rst
docs/installation.rst
docs/make.bat
docs/readme.rst
docs/usage.rst
tests/test_whiplash.py
whiplash/__init__.py
whiplash/whiplash.py
whiplash.egg-info/PKG-INFO
whiplash.egg-info/SOURCES.txt
whiplash.egg-info/dependency_links.txt
whiplash.egg-info/not-zip-safe
whiplash.egg-info/requires.txt
whiplash.egg-info/top_level.txt