Metadata-Version: 1.1
Name: whiplash
Version: 0.1.0
Summary: Python API Client for the whiplash API
Home-page: https://github.com/fulfilio/whiplash
Author: Fulfil.IO Inc.
Author-email: hello@fulfil.io
License: BSD
Keywords: whiplash
Platform: UNKNOWN
Classifier: Development Status :: 2 - Pre-Alpha
Classifier: Intended Audience :: Developers
Classifier: License :: OSI Approved :: ISC License (ISCL)
Classifier: Natural Language :: English
Classifier: Programming Language :: Python :: 2
Classifier: Programming Language :: Python :: 2.6
Classifier: Programming Language :: Python :: 2.7
Classifier: Programming Language :: Python :: 3
Classifier: Programming Language :: Python :: 3.3
Classifier: Programming Language :: Python :: 3.4
